Workbook

Sheet README
A1: Burberry Group plc (LON:BRBY) — 5-Year DCF Valuation Model
A3: Prepared by: Abia Khan | khan.abia1013@gmail.com
A5: DATA AS OF: 15 August 2026. Historical financials sourced from stockanalysis.com (Fiscal.ai data), cross-checked
A6: against Burberry Group plc Annual Report FY2025/26 (burberryplc.com/investors). Full URLs on the Sources tab.
A8: KEY JUDGEMENT CALLS:
A9: 1. Revenue growth (FY2027-31): Burberry is mid-turnaround — FY2026 revenue was still down YoY, but Q1 FY2027
A10: (to 27 Jun 2026) showed +5% comparable retail sales and a return to growth in every division. The forecast
A11: assumes a moderate recovery (3.0% -> 4.0% -> 4.0% -> 3.5% -> 3.0%), NOT a straight-line extrapolation of any
A12: single quarter.
A13: 2. EBITDA margin: FY2025 margin (16.7%) was depressed by turnaround/impairment charges; FY2022-23 pre-turnaround
A14: margins were 30%+. The forecast assumes gradual recovery to 25.5% by Year 5 — below the pre-2024 peak, on the
A15: basis that full margin restoration is not yet demonstrated in reported results.
... A24: uses the UK statutory corporate tax rate of 25% for all forecast years, per standard DCF practice.

Sheet Historicals
A1: Burberry Group — Historical Financials (£m)
A2: Fiscal year April-March. Blue = hardcoded input. Source: stockanalysis.com (Fiscal.ai), cross-checked vs Annual Report FY2025/26.
A4: £m — FY ending March | B4: FY2022 | C4: FY2023 | D4: FY2024 | E4: FY2025 | F4: FY2026
A5: Revenue | B5: 2826 | C5: 3094 | D5: 2968 | E5: 2461 | F5: 2420
A6: Revenue growth % | C6: =C5/B5-1 -> 0.094833687 | D6: =D5/C5-1 -> -0.040723982 | E6: =E5/D5-1 -> -0.1708221 | F6: =F5/E5-1 -> -0.016659894
A7: EBITDA | B7: 856 | C7: 1001 | D7: 797 | E7: 410 | F7: 490
A8: EBITDA margin % | B8: =B7/B5 -> 0.30290163 | C8: =C7/C5 -> 0.32352941 | D8: =D7/D5 -> 0.268531 | E8: =E7/E5 -> 0.16659894 | F8: =F7/F5 -> 0.20247934
A9: EBIT (Operating Income) | B9: 543 | C9: 657 | D9: 418 | E9: -3 | F9: 115
A10: D&A (EBITDA - EBIT) | B10: =B7-B9 -> 313 | C10: =C7-C9 -> 344 | D10: =D7-D9 -> 379 | E10: =E7-E9 -> 413 | F10: =F7-F9 -> 375
A11: Net Income | B11: 396 | C11: 490 | D11: 270 | E11: -75 | F11: 21
A12: Capex (incl. intangibles) | B12: 161 | C12: 179 | D12: 208 | E12: 151 | F12: 113
A13: Diluted shares (m) | B13: 405 | C13: 388 | D13: 366 | E13: 357 | F13: 358.21
A14: Total Debt | B14: 1401 | C14: 1486 | D14: 1566 | E14: 1924 | F14: 1523
A15: Cash & equivalents | B15: 1222 | C15: 1026 | D15: 441 | E15: 813 | F15: 671
A16: Net Debt | B16: =B14-B15 -> 179 | C16: =C14-C15 -> 460 | D16: =D14-D15 -> 1125 | E16: =E14-E15 -> 1111 | F16: =F14-F15 -> 852
A18: Net Working Capital (FY2026 base, ~11.5% of revenue — see Assumptions methodology) | F18: =F5*0.115 -> 278.3
A19: Base-year NWC estimated at 11.5% of FY2026 revenue (see Assumptions tab methodology), used only as the FY2027 opening balance for the change-in-NWC calc.
A20: Net Income FY2025 and EBIT FY2025 were negative — reflects turnaround/impairment charges disclosed in the FY2024/25 Annual Report.

Sheet Assumptions
A1: Forecast Assumptions — FY2027-FY2031
A2: All blue cells are the only inputs that drive the forecast. Edit here, not inside formulas elsewhere.
A4: Driver | B4: FY2027E | C4: FY2028E | D4: FY2029E | E4: FY2030E | F4: FY2031E
A5: Revenue growth % | B5: 0.03 | C5: 0.04 | D5: 0.04 | E5: 0.035 | F5: 0.03
A6: EBITDA margin % | B6: 0.21 | C6: 0.225 | D6: 0.24 | E6: 0.25 | F6: 0.255
A7: D&A (% of revenue) | B7: 0.15 | C7: 0.148 | D7: 0.145 | E7: 0.143 | F7: 0.14
A8: CapEx (% of revenue) | B8: 0.047 | C8: 0.046 | D8: 0.045 | E8: 0.045 | F8: 0.045
A9: Net Working Capital (% of revenue) | B9: 0.128 | C9: 0.125 | D9: 0.122 | E9: 0.12 | F9: 0.12
A10: Tax rate % | B10: 0.25 | C10: 0.25 | D10: 0.25 | E10: 0.25 | F10: 0.25
A12: Terminal growth rate (g) | B12: 0.025
A13: WACC (linked from WACC tab) | B13: =WACC!B18 -> 0.074860078
A15: Revenue growth: moderate turnaround recovery (Q1 FY2027 comparable sales +5%, all divisions returned to growth per
A16: 17 Jul 2026 trading statement), tapering toward a ~3% long-run rate. This is a judgement call, not a consensus figure.
A17: EBITDA margin: gradual recovery from FY2026's 20.3% toward 25.5% by Year 5 — below the pre-turnaround 30%+ peak (FY2022-23),
A18: reflecting that full margin restoration is not yet evidenced in reported results.
A19: D&A % and CapEx %: held roughly at FY2026 actual levels (15.5% and 4.7% of revenue respectively), tapering slightly.
A20: NWC %: based on FY2025-26 average (Net Working Capital / Revenue = 14.1% and 11.5% respectively; see Historicals tab).
A21: Tax rate: UK statutory corporate tax rate (25%), per standard DCF practice, since FY2026's reported effective rate
A22: (59.2%) is distorted by near-zero pre-tax income.
A23: Terminal growth: set below UK nominal GDP trend (~3.5-4%) and at the low end of typical luxury-sector long-run
A24: assumptions (2-3%), consistent with Gordon Growth Model convention that g must stay below WACC.

Sheet Forecast IS & FCF
A1: Forecast Income Statement & Unlevered Free Cash Flow (£m)
A3: £m | B3: FY2027E | C3: FY2028E | D3: FY2029E | E3: FY2030E | F3: FY2031E
A4: Revenue | B4: =Historicals!F5*(1+Assumptions!B5) -> 2492.6 | C4: =B4*(1+Assumptions!C5) -> 2592.304 | D4: =C4*(1+Assumptions!D5) -> 2695.9962 | E4: =D4*(1+Assumptions!E5) -> 2790.356 | F4: =E4*(1+Assumptions!F5) -> 2874.0667
A5: growth % | B5: =Assumptions!B5 -> 0.03 | C5: =Assumptions!C5 -> 0.04 | D5: =Assumptions!D5 -> 0.04 | E5: =Assumptions!E5 -> 0.035 | F5: =Assumptions!F5 -> 0.03
A6: EBITDA | B6: =B4*Assumptions!B6 -> 523.446 | C6: =C4*Assumptions!C6 -> 583.2684 | D6: =D4*Assumptions!D6 -> 647.03908 | E6: =E4*Assumptions!E6 -> 697.58901 | F6: =F4*Assumptions!F6 -> 732.88701
A7: margin % | B7: =Assumptions!B6 -> 0.21 | C7: =Assumptions!C6 -> 0.225 | D7: =Assumptions!D6 -> 0.24 | E7: =Assumptions!E6 -> 0.25 | F7: =Assumptions!F6 -> 0.255
A8: D&A | B8: =B4*Assumptions!B7 -> 373.89 | C8: =C4*Assumptions!C7 -> 383.66099 | D8: =D4*Assumptions!D7 -> 390.91944 | E8: =E4*Assumptions!E7 -> 399.02091 | F8: =F4*Assumptions!F7 -> 402.36934
A9: EBIT | B9: =B6-B8 -> 149.556 | C9: =C6-C8 -> 199.60741 | D9: =D6-D8 -> 256.11964 | E9: =E6-E8 -> 298.56809 | F9: =F6-F8 -> 330.51767
A10: Tax on EBIT (unlevered) | B10: =B9*Assumptions!B10 -> 37.389 | C10: =C9*Assumptions!C10 -> 49.901852 | D10: =D9*Assumptions!D10 -> 64.029909 | E10: =E9*Assumptions!E10 -> 74.642024 | F10: =F9*Assumptions!F10 -> 82.629418
A11: NOPAT (EBIT x (1-tax)) | B11: =B9-B10 -> 112.167 | C11: =C9-C10 -> 149.70556 | D11: =D9-D10 -> 192.08973 | E11: =E9-E10 -> 223.92607 | F11: =F9-F10 -> 247.88825
A12: Add back: D&A | B12: =B8 -> 373.89 | C12: =C8 -> 383.66099 | D12: =D8 -> 390.91944 | E12: =E8 -> 399.02091 | F12: =F8 -> 402.36934
A13: Less: CapEx | B13: =-B4*Assumptions!B8 -> -117.1522 | C13: =-C4*Assumptions!C8 -> -119.24598 | D13: =-D4*Assumptions!D8 -> -121.31983 | E13: =-E4*Assumptions!E8 -> -125.56602 | F13: =-F4*Assumptions!F8 -> -129.333
A14: Net Working Capital | B14: =B4*Assumptions!B9 -> 319.0528 | C14: =C4*Assumptions!C9 -> 324.038 | D14: =D4*Assumptions!D9 -> 328.91153 | E14: =E4*Assumptions!E9 -> 334.84272 | F14: =F4*Assumptions!F9 -> 344.888
A15: Increase / (decrease) in NWC | B15: =B14-Historicals!F18 -> 40.7528 | C15: =C14-B14 -> 4.9852 | D15: =D14-C14 -> 4.8735315 | E15: =E14-D14 -> 5.9311916 | F15: =F14-E14 -> 10.045282
A16: Unlevered Free Cash Flow | B16: =B11+B12+B13-B15 -> 328.152 | C16: =C11+C12+C13-C15 -> 409.13536 | D16: =D11+D12+D13-D15 -> 456.81581 | E16: =E11+E12+E13-E15 -> 491.44977 | F16: =F11+F12+F13-F15 -> 510.87931
A18: NOPAT = EBIT x (1 - tax rate). Using NOPAT (not net income) for unlevered FCF is standard DCF practice — it excludes financing effects (interest) so the
A19: resulting Enterprise Value is capital-structure-neutral, matching the discount rate (WACC) used.

Sheet WACC
A1: Weighted Average Cost of Capital (WACC)
A3: Input | B3: Value
A4: Risk-free rate (UK 10yr Gilt yield) | B4: 0.0497 | C4: Source: TradingEconomics, UK 10Y Government Bond Yield, 13 Aug 2026
A5: Beta (5yr, vs FTSE All-Share) | B5: 0.75 | C5: Source: stockanalysis.com/quote/lon/BRBY/statistics/, 15 Aug 2026
A6: Equity Risk Premium (assumed) | B6: 0.05 | C6: Source: Standard UK ERP assumption (5%)
A7: Cost of Equity (CAPM) = Rf + Beta x ERP | B7: =B4+B5*B6 -> 0.0872
A9: Interest expense FY2026 (£m) | B9: 89 | C9: Source: stockanalysis.com Income Statement, FY2026 (Interest Expense).
A10: Total debt FY2026 (£m) | B10: =Historicals!F14 -> 1523
A11: Pre-tax cost of debt = Interest / Total Debt | B11: =B9/B10 -> 0.058437295
A12: Tax rate | B12: =Assumptions!B10 -> 0.25
A13: After-tax cost of debt | B13: =B11*(1-B12) -> 0.043827971
A15: Market value of equity (£m) — market cap | B15: 3830 | C15: Source: trading comps build, Data tab (Market Cap £m), 5 Aug 2026.
A16: Market value of debt (£m) — total debt (proxy) | B16: =B10 -> 1523
A17: Weight of equity / Weight of debt | B17: =B15/(B15+B16) -> 0.71548664 | C17: ="Debt weight: "&TEXT(B16/(B15+B16),"0.0%") -> Debt weight: 28.5%
A18: WACC = We x Ke + Wd x Kd(after-tax) | B18: =B17*B7+(1-B17)*B13 -> 0.074860078
A20: Book value of debt is used as a proxy for market value of debt, standard practice absent quoted bond prices for Burberry's private debt facilities.

Sheet DCF Output
A1: DCF Output — Enterprise Value to Implied Share Price
A3: £m | B3: FY2027E | C3: FY2028E | D3: FY2029E | E3: FY2030E | F3: FY2031E
A4: Unlevered FCF | B4: ='Forecast IS & FCF'!B16 -> 328.152 | C4: ='Forecast IS & FCF'!C16 -> 409.13536 | D4: ='Forecast IS & FCF'!D16 -> 456.81581 | E4: ='Forecast IS & FCF'!E16 -> 491.44977 | F4: ='Forecast IS & FCF'!F16 -> 510.87931
A5: Discount period (t) | B5: =1 -> 1 | C5: =2 -> 2 | D5: =3 -> 3 | E5: =4 -> 4 | F5: =5 -> 5
A6: Discount factor = 1/(1+WACC)^t | B6: =1/(1+WACC!$B$18)^B5 -> 0.93035365 | C6: =1/(1+WACC!$B$18)^C5 -> 0.86555792 | D6: =1/(1+WACC!$B$18)^D5 -> 0.80527497 | E6: =1/(1+WACC!$B$18)^E5 -> 0.74919051 | F6: =1/(1+WACC!$B$18)^F5 -> 0.69701213
A7: PV of FCF | B7: =B4*B6 -> 305.29741 | C7: =C4*C6 -> 354.13035 | D7: =D4*D6 -> 367.86234 | E7: =E4*E6 -> 368.1895 | F7: =F4*F6 -> 356.08907
A9: Sum of PV of FCF (Years 1-5) | B9: =SUM(B7:F7) -> 1751.5687
A11: Terminal Value (Gordon Growth Method)
A12: Year 5 Unlevered FCF | B12: =F4 -> 510.87931
A13: Terminal growth rate (g) | B13: =Assumptions!B12 -> 0.025
A14: Terminal Value = FCF5 x (1+g) / (WACC - g) | B14: =B12*(1+B13)/(WACC!$B$18-B13) -> 10502.416
A15: PV of Terminal Value | B15: =B14*F6 -> 7320.3114
A17: Enterprise Value = Sum PV(FCF) + PV(TV) | B17: =B9+B15 -> 9071.8801
A18: TV as % of Enterprise Value | B18: =B15/B17 -> 0.8069233
A20: Less: Net Debt (FY2026 balance sheet) | B20: =-Historicals!F16 -> -852
A21: Equity Value | B21: =B17+B20 -> 8219.8801
A22: Diluted shares outstanding (m) | B22: =Historicals!F13 -> 358.21
A23: Implied share price (£) | B23: =B21/B22 -> 22.947098
A25: Current share price (£) | B25: 10.715 | C25: Source: trading comps build, Data tab (Current Share Price, native GBP), 5 Aug 2026 — used here rather than a separately-fetched live quote so both | D25: models anchor to the exact same current price and upside/downside % is directly comparable across methodologies.
A26: Implied upside / (downside) | B26: =B23/B25-1 -> 1.1415864
A28: Note: FCF is discounted using a mid-year-convention-free (end-of-year) DCF for simplicity.
A29: TV as % of EV is typically 60-80% in a 5-year DCF; check this figure as a sanity test whenever assumptions change materially.

Sheet Sensitivity
A1: Sensitivity — Implied Share Price (£) vs WACC and Terminal Growth
A2: Manually computed 2-variable grid (values are formula-driven — no volatile Data Table needed).
A4: WACC \ Terminal g | B4: =Assumptions!$B$12+(-0.01) -> 0.015 | C4: =Assumptions!$B$12+(-0.005) -> 0.02 | D4: =Assumptions!$B$12+(0) -> 0.025 | E4: =Assumptions!$B$12+(0.005) -> 0.03 | F4: =Assumptions!$B$12+(0.01) -> 0.035
A5: =WACC!$B$18+(-0.01) -> 0.064860078 | B5: =(('Forecast IS & FCF'!$B$16/(1+$A5)^1+'Forecast IS & FCF'!$C$16/(1+$A5)^2+'Forecast IS & FCF'!$D$16/(1+$A5)^3+'Forecast IS & FCF'!$E$16/(1+$A5)^4+'Forecast IS & FCF'!$F$16/(1+$A5)^5)+('Forecast IS & FCF'!$F$16*(1+B$4))/($A5-B$4)/(1+$A5)^5-Historicals!$F$16)/Historicals!$F$13 -> 23.858514 | C5: =(('Forecast IS & FCF'!$B$16/(1+$A5)^1+'Forecast IS & FCF'!$C$16/(1+$A5)^2+'Forecast IS & FCF'!$D$16/(1+$A5)^3+'Forecast IS & FCF'!$E$16/(1+$A5)^4+'Forecast IS & FCF'!$F$16/(1+$A5)^5)+('Forecast IS & FCF'!$F$16*(1+C$4))/($A5-C$4)/(1+$A5)^5-Historicals!$F$16)/Historicals!$F$13 -> 26.338033 | D5: =(('Forecast IS & FCF'!$B$16/(1+$A5)^1+'Forecast IS & FCF'!$C$16/(1+$A5)^2+'Forecast IS & FCF'!$D$16/(1+$A5)^3+'Forecast IS & FCF'!$E$16/(1+$A5)^4+'Forecast IS & FCF'!$F$16/(1+$A5)^5)+('Forecast IS & FCF'!$F$16*(1+D$4))/($A5-D$4)/(1+$A5)^5-Historicals!$F$16)/Historicals!$F$13 -> 29.439607 | E5: =(('Forecast IS & FCF'!$B$16/(1+$A5)^1+'Forecast IS & FCF'!$C$16/(1+$A5)^2+'Forecast IS & FCF'!$D$16/(1+$A5)^3+'Forecast IS & FCF'!$E$16/(1+$A5)^4+'Forecast IS & FCF'!$F$16/(1+$A5)^5)+('Forecast IS & FCF'!$F$16*(1+E$4))/($A5-E$4)/(1+$A5)^5-Historicals!$F$16)/Historicals!$F$13 -> 33.430903 | F5: =(('Forecast IS & FCF'!$B$16/(1+$A5)^1+'Forecast IS & FCF'!$C$16/(1+$A5)^2+'Forecast IS & FCF'!$D$16/(1+$A5)^3+'Forecast IS & FCF'!$E$16/(1+$A5)^4+'Forecast IS & FCF'!$F$16/(1+$A5)^5)+('Forecast IS & FCF'!$F$16*(1+F$4))/($A5-F$4)/(1+$A5)^5-Historicals!$F$16)/Historicals!$F$13 -> 38.758865
A6: =WACC!$B$18+(-0.005) -> 0.069860078 | B6: =(('Forecast IS & FCF'!$B$16/(1+$A6)^1+'Forecast IS & FCF'!$C$16/(1+$A6)^2+'Forecast IS & FCF'!$D$16/(1+$A6)^3+'Forecast IS & FCF'!$E$16/(1+$A6)^4+'Forecast IS & FCF'!$F$16/(1+$A6)^5)+('Forecast IS & FCF'!$F$16*(1+B$4))/($A6-B$4)/(1+$A6)^5-Historicals!$F$16)/Historicals!$F$13 -> 21.407678 | C6: =(('Forecast IS & FCF'!$B$16/(1+$A6)^1+'Forecast IS & FCF'!$C$16/(1+$A6)^2+'Forecast IS & FCF'!$D$16/(1+$A6)^3+'Forecast IS & FCF'!$E$16/(1+$A6)^4+'Forecast IS & FCF'!$F$16/(1+$A6)^5)+('Forecast IS & FCF'!$F$16*(1+C$4))/($A6-C$4)/(1+$A6)^5-Historicals!$F$16)/Historicals!$F$13 -> 23.397588 | D6: =(('Forecast IS & FCF'!$B$16/(1+$A6)^1+'Forecast IS & FCF'!$C$16/(1+$A6)^2+'Forecast IS & FCF'!$D$16/(1+$A6)^3+'Forecast IS & FCF'!$E$16/(1+$A6)^4+'Forecast IS & FCF'!$F$16/(1+$A6)^5)+('Forecast IS & FCF'!$F$16*(1+D$4))/($A6-D$4)/(1+$A6)^5-Historicals!$F$16)/Historicals!$F$13 -> 25.831078 | E6: =(('Forecast IS & FCF'!$B$16/(1+$A6)^1+'Forecast IS & FCF'!$C$16/(1+$A6)^2+'Forecast IS & FCF'!$D$16/(1+$A6)^3+'Forecast IS & FCF'!$E$16/(1+$A6)^4+'Forecast IS & FCF'!$F$16/(1+$A6)^5)+('Forecast IS & FCF'!$F$16*(1+E$4))/($A6-E$4)/(1+$A6)^5-Historicals!$F$16)/Historicals!$F$13 -> 28.875077 | F6: =(('Forecast IS & FCF'!$B$16/(1+$A6)^1+'Forecast IS & FCF'!$C$16/(1+$A6)^2+'Forecast IS & FCF'!$D$16/(1+$A6)^3+'Forecast IS & FCF'!$E$16/(1+$A6)^4+'Forecast IS & FCF'!$F$16/(1+$A6)^5)+('Forecast IS & FCF'!$F$16*(1+F$4))/($A6-F$4)/(1+$A6)^5-Historicals!$F$16)/Historicals!$F$13 -> 32.792281
A7: =WACC!$B$18+(0) -> 0.074860078 | B7: =(('Forecast IS & FCF'!$B$16/(1+$A7)^1+'Forecast IS & FCF'!$C$16/(1+$A7)^2+'Forecast IS & FCF'!$D$16/(1+$A7)^3+'Forecast IS & FCF'!$E$16/(1+$A7)^4+'Forecast IS & FCF'!$F$16/(1+$A7)^5)+('Forecast IS & FCF'!$F$16*(1+B$4))/($A7-B$4)/(1+$A7)^5-Historicals!$F$16)/Historicals!$F$13 -> 19.367102 | C7: =(('Forecast IS & FCF'!$B$16/(1+$A7)^1+'Forecast IS & FCF'!$C$16/(1+$A7)^2+'Forecast IS & FCF'!$D$16/(1+$A7)^3+'Forecast IS & FCF'!$E$16/(1+$A7)^4+'Forecast IS & FCF'!$F$16/(1+$A7)^5)+('Forecast IS & FCF'!$F$16*(1+C$4))/($A7-C$4)/(1+$A7)^5-Historicals!$F$16)/Historicals!$F$13 -> 20.993958 | D7: =(('Forecast IS & FCF'!$B$16/(1+$A7)^1+'Forecast IS & FCF'!$C$16/(1+$A7)^2+'Forecast IS & FCF'!$D$16/(1+$A7)^3+'Forecast IS & FCF'!$E$16/(1+$A7)^4+'Forecast IS & FCF'!$F$16/(1+$A7)^5)+('Forecast IS & FCF'!$F$16*(1+D$4))/($A7-D$4)/(1+$A7)^5-Historicals!$F$16)/Historicals!$F$13 -> 22.947098 | E7: =(('Forecast IS & FCF'!$B$16/(1+$A7)^1+'Forecast IS & FCF'!$C$16/(1+$A7)^2+'Forecast IS & FCF'!$D$16/(1+$A7)^3+'Forecast IS & FCF'!$E$16/(1+$A7)^4+'Forecast IS & FCF'!$F$16/(1+$A7)^5)+('Forecast IS & FCF'!$F$16*(1+E$4))/($A7-E$4)/(1+$A7)^5-Historicals!$F$16)/Historicals!$F$13 -> 25.335624 | F7: =(('Forecast IS & FCF'!$B$16/(1+$A7)^1+'Forecast IS & FCF'!$C$16/(1+$A7)^2+'Forecast IS & FCF'!$D$16/(1+$A7)^3+'Forecast IS & FCF'!$E$16/(1+$A7)^4+'Forecast IS & FCF'!$F$16/(1+$A7)^5)+('Forecast IS & FCF'!$F$16*(1+F$4))/($A7-F$4)/(1+$A7)^5-Historicals!$F$16)/Historicals!$F$13 -> 28.323377
A8: =WACC!$B$18+(0.005) -> 0.079860078 | B8: =(('Forecast IS & FCF'!$B$16/(1+$A8)^1+'Forecast IS & FCF'!$C$16/(1+$A8)^2+'Forecast IS & FCF'!$D$16/(1+$A8)^3+'Forecast IS & FCF'!$E$16/(1+$A8)^4+'Forecast IS & FCF'!$F$16/(1+$A8)^5)+('Forecast IS & FCF'!$F$16*(1+B$4))/($A8-B$4)/(1+$A8)^5-Historicals!$F$16)/Historicals!$F$13 -> 17.641888 | C8: =(('Forecast IS & FCF'!$B$16/(1+$A8)^1+'Forecast IS & FCF'!$C$16/(1+$A8)^2+'Forecast IS & FCF'!$D$16/(1+$A8)^3+'Forecast IS & FCF'!$E$16/(1+$A8)^4+'Forecast IS & FCF'!$F$16/(1+$A8)^5)+('Forecast IS & FCF'!$F$16*(1+C$4))/($A8-C$4)/(1+$A8)^5-Historicals!$F$16)/Historicals!$F$13 -> 18.99261 | D8: =(('Forecast IS & FCF'!$B$16/(1+$A8)^1+'Forecast IS & FCF'!$C$16/(1+$A8)^2+'Forecast IS & FCF'!$D$16/(1+$A8)^3+'Forecast IS & FCF'!$E$16/(1+$A8)^4+'Forecast IS & FCF'!$F$16/(1+$A8)^5)+('Forecast IS & FCF'!$F$16*(1+D$4))/($A8-D$4)/(1+$A8)^5-Historicals!$F$16)/Historicals!$F$13 -> 20.589544 | E8: =(('Forecast IS & FCF'!$B$16/(1+$A8)^1+'Forecast IS & FCF'!$C$16/(1+$A8)^2+'Forecast IS & FCF'!$D$16/(1+$A8)^3+'Forecast IS & FCF'!$E$16/(1+$A8)^4+'Forecast IS & FCF'!$F$16/(1+$A8)^5)+('Forecast IS & FCF'!$F$16*(1+E$4))/($A8-E$4)/(1+$A8)^5-Historicals!$F$16)/Historicals!$F$13 -> 22.506761 | F8: =(('Forecast IS & FCF'!$B$16/(1+$A8)^1+'Forecast IS & FCF'!$C$16/(1+$A8)^2+'Forecast IS & FCF'!$D$16/(1+$A8)^3+'Forecast IS & FCF'!$E$16/(1+$A8)^4+'Forecast IS & FCF'!$F$16/(1+$A8)^5)+('Forecast IS & FCF'!$F$16*(1+F$4))/($A8-F$4)/(1+$A8)^5-Historicals!$F$16)/Historicals!$F$13 -> 24.851355
A9: =WACC!$B$18+(0.01) -> 0.084860078 | B9: =(('Forecast IS & FCF'!$B$16/(1+$A9)^1+'Forecast IS & FCF'!$C$16/(1+$A9)^2+'Forecast IS & FCF'!$D$16/(1+$A9)^3+'Forecast IS & FCF'!$E$16/(1+$A9)^4+'Forecast IS & FCF'!$F$16/(1+$A9)^5)+('Forecast IS & FCF'!$F$16*(1+B$4))/($A9-B$4)/(1+$A9)^5-Historicals!$F$16)/Historicals!$F$13 -> 16.16431 | C9: =(('Forecast IS & FCF'!$B$16/(1+$A9)^1+'Forecast IS & FCF'!$C$16/(1+$A9)^2+'Forecast IS & FCF'!$D$16/(1+$A9)^3+'Forecast IS & FCF'!$E$16/(1+$A9)^4+'Forecast IS & FCF'!$F$16/(1+$A9)^5)+('Forecast IS & FCF'!$F$16*(1+C$4))/($A9-C$4)/(1+$A9)^5-Historicals!$F$16)/Historicals!$F$13 -> 17.300495 | D9: =(('Forecast IS & FCF'!$B$16/(1+$A9)^1+'Forecast IS & FCF'!$C$16/(1+$A9)^2+'Forecast IS & FCF'!$D$16/(1+$A9)^3+'Forecast IS & FCF'!$E$16/(1+$A9)^4+'Forecast IS & FCF'!$F$16/(1+$A9)^5)+('Forecast IS & FCF'!$F$16*(1+D$4))/($A9-D$4)/(1+$A9)^5-Historicals!$F$16)/Historicals!$F$13 -> 18.626487 | E9: =(('Forecast IS & FCF'!$B$16/(1+$A9)^1+'Forecast IS & FCF'!$C$16/(1+$A9)^2+'Forecast IS & FCF'!$D$16/(1+$A9)^3+'Forecast IS & FCF'!$E$16/(1+$A9)^4+'Forecast IS & FCF'!$F$16/(1+$A9)^5)+('Forecast IS & FCF'!$F$16*(1+E$4))/($A9-E$4)/(1+$A9)^5-Historicals!$F$16)/Historicals!$F$13 -> 20.194184 | F9: =(('Forecast IS & FCF'!$B$16/(1+$A9)^1+'Forecast IS & FCF'!$C$16/(1+$A9)^2+'Forecast IS & FCF'!$D$16/(1+$A9)^3+'Forecast IS & FCF'!$E$16/(1+$A9)^4+'Forecast IS & FCF'!$F$16/(1+$A9)^5)+('Forecast IS & FCF'!$F$16*(1+F$4))/($A9-F$4)/(1+$A9)^5-Historicals!$F$16)/Historicals!$F$13 -> 22.0763
A11: Row = WACC scenario (base WACC +/- 1.0%). Column = Terminal growth scenario (base g +/- 1.0%).
A12: Formula recomputes EV, subtracts net debt, and divides by diluted shares for each WACC/g pair — mechanically equivalent to Excel's Data Table but avoids the
A13: circular-reference / iterative-calc issues that Data Tables can cause when reopened outside Excel.

Sheet Sources
A1: Data Sources
A3: Item | B3: Source / URL
A4: Income Statement (FY2022-26) | B4: https://stockanalysis.com/quote/lon/BRBY/financials/ — pulled 15 Aug 2026
A5: Balance Sheet (FY2022-26) | B5: https://stockanalysis.com/quote/lon/BRBY/financials/balance-sheet/ — pulled 15 Aug 2026
A6: Cash Flow Statement (FY2022-26) | B6: https://stockanalysis.com/quote/lon/BRBY/financials/cash-flow-statement/ — pulled 15 Aug 2026
A7: Beta (5yr) | B7: https://stockanalysis.com/quote/lon/BRBY/statistics/ — pulled 15 Aug 2026 (Beta = 0.75)
A8: Risk-free rate (UK 10yr Gilt) | B8: https://tradingeconomics.com/united-kingdom/government-bond-yield — 13 Aug 2026 close, ~4.97%
A9: Current share price (31 Jul 2026) | B9: https://stockanalysis.com/quote/lon/BRBY/financials/balance-sheet/ (page header quote) — 1,211.00 GBX
A10: Market cap (5 Aug 2026) | B10: Companion workbook: Burberry_Luxury_Comps_Model_CV.xlsx, Data tab, sourced stockanalysis.com/quote/lon/BRBY/statistics/
A11: Q1 FY2027 trading statement | B11: Burberry Group plc Q1 2027 Trading Statement, 17 Jul 2026, burberryplc.com/investors — comparable retail sales +5%
A12: FY2025/26 KPIs (Adjusted operating profit) | B12: https://www.burberryplc.com/investors/financial-performance-kpis
A13: Equity Risk Premium | B13: Standard UK/developed-market ERP assumption — not a single-source published figure.
