Workbook

Sheet README
A1: Greggs plc (LON:GRG) — Leveraged Buyout (LBO) Model
A3: Prepared by: Abia Khan | khan.abia1013@gmail.com
A5: WHY GREGGS, NOT BURBERRY: LBOs work on cash-generative, low-volatility businesses that can service debt reliably.
A6: Burberry (used for the Comps and DCF models) is mid-turnaround with volatile/near-zero net income — a poor LBO
A7: candidate. Greggs is a stable, cash-generative UK consumer staples business (food-on-the-go bakery retail), which
A8: is the textbook LBO profile.
A10: DATA AS OF: 15 August 2026. Source: stockanalysis.com (Fiscal.ai data). Full URLs on the Sources tab.
A12: KEY JUDGEMENT CALLS:
A13: 1. Entry multiple: set at 6.2x EBITDA, in line with Greggs' current trading EV/EBITDA (~6.1-6.2x as of Aug 2026,
A14: per stockanalysis.com), i.e. NOT a takeover premium — this models a 'take-private at market' scenario, the most
A15: defensible base case for a company with no live bid. A real sponsor would typically pay a 20-30% premium; that
A16: would proportionally lower IRR, which the sensitivity table lets you see directly.
... A25: common alternative but assumes zero reinvestment need, which is unrealistic for a growing store estate).

Sheet Transaction Assumptions
A1: Transaction Assumptions
A3: Input | B3: Value
A4: Target FY2025 EBITDA (£m) | B4: 344.3 | C4: stockanalysis.com Income Statement, FY2025 (Jan-Dec fiscal year) | E4: <- Year-0 Revenue base (£m) | F4: =B4/0.16 -> 2151.875
A5: Entry EV/EBITDA multiple | B5: 6.2 | C5: stockanalysis.com Statistics, EV/EBITDA ~6.1-6.2x, 15 Aug 2026 (current trading multiple, no premium)
A6: Transaction fees (% of EV) | B6: 0.02 | C6: Standard LBO assumption (~2% of EV)
A7: New Term Loan (x EBITDA) | B7: 4.5 | C7: Mid-point of a 4-5x EBITDA range typical for a stable consumer staples credit
A8: Term Loan interest rate (SOFR/Base + spread) | B8: 0.0897 | C8: BoE Bank Rate ~4.0% (Aug 2026) + ~490bps leveraged loan spread, illustrative
A9: Mandatory amortisation (% of Term Loan / yr) | B9: 0.05 | C9: Standard institutional Term Loan B convention
A10: Cash sweep (% of excess FCF swept to debt) | B10: 0.8 | C10: 80% (not 100%) allows for reinvestment
A11: Existing net debt refinanced (£m) | B11: 404 | C11: stockanalysis.com Statistics: Total debt £474.8m less cash £70.8m, 15 Aug 2026
A12: Revenue growth Year 1-5 (avg) | B12: 0.065 | C12: In line with FY2023-25 average reported growth (6.8-19.6%, decelerating) — see Historicals
A13: Tax rate | B13: 0.25 | C13: UK statutory corporate tax rate
A14: Exit year | B14: 5 | C14: Standard 5-year LBO hold period
A15: Exit EV/EBITDA multiple | B15: 6.2 | C15: Equal to entry multiple (conservative, no multiple expansion assumed — see README)
A17: Revenue growth by year:
B18: Yr1 | C18: Yr2 | D18: Yr3 | E18: Yr4 | F18: Yr5
A19: Revenue growth % | B19: 0.075 | C19: 0.07 | D19: 0.065 | E19: 0.06 | F19: 0.055
A20: EBITDA margin % | B20: 0.163 | C20: 0.166 | D20: 0.169 | E20: 0.172 | F20: 0.175
A22: Revenue growth tapers from FY2023-25 average (~12.5%) toward a more mature 5.5-7.5% range, reflecting continued UK store rollout slowing as the estate matures.
A23: EBITDA margin: FY2025 actual 16.0% + ~30bps/year 'operational improvement' (cost discipline / supply chain), a conservative assumption flagged per README.

Sheet Sources & Uses
A1: Sources & Uses of Funds (£m)
A3: Uses | B3: £m | C3: Sources | D3: £m
A4: Entry EV = EBITDA x Entry Multiple | B4: ='Transaction Assumptions'!B4*'Transaction Assumptions'!B5 -> 2134.66 | C4: New Term Loan (x EBITDA) | D4: ='Transaction Assumptions'!B4*'Transaction Assumptions'!B7 -> 1549.35
A5: Purchase of Equity (= Entry EV - existing net debt) | B5: =B4-'Transaction Assumptions'!B11 -> 1730.66 | C5: New Revolver (undrawn at close) | D5: 0
A6: Refinance existing net debt | B6: ='Transaction Assumptions'!B11 -> 404 | C6: Sponsor Equity (plug) | D6: =B8-D4-D5 -> 628.0032
A7: Transaction fees (% of EV) | B7: =B4*'Transaction Assumptions'!B6 -> 42.6932
A8: Total Uses | B8: =B5+B6+B7 -> 2177.3532 | C8: Total Sources | D8: =D4+D5+D6 -> 2177.3532
A10: Check: Sources = Uses | B10: =D8-B8 -> 0
A12: Entry leverage: Total Debt / EBITDA | B12: =D4/'Transaction Assumptions'!B4 -> 4.5
A13: Sponsor equity as % of Total Sources | B13: =D6/D8 -> 0.28842505

Sheet Debt Schedule
A1: Term Loan Debt Schedule (£m)
A3: £m | B3: Year 1 | C3: Year 2 | D3: Year 3 | E3: Year 4 | F3: Year 5
A4: Opening Term Loan balance | B4: ='Sources & Uses'!D4 -> 1549.35 | C4: =B8 -> 1471.8825 | D4: =C8 -> 1394.415 | E4: =D8 -> 1316.9475 | F4: =E8 -> 1239.48
A5: Mandatory amortisation | B5: =MIN(B4,'Sources & Uses'!$D$4*'Transaction Assumptions'!$B$9) -> 77.4675 | C5: =MIN(C4,'Sources & Uses'!$D$4*'Transaction Assumptions'!$B$9) -> 77.4675 | D5: =MIN(D4,'Sources & Uses'!$D$4*'Transaction Assumptions'!$B$9) -> 77.4675 | E5: =MIN(E4,'Sources & Uses'!$D$4*'Transaction Assumptions'!$B$9) -> 77.4675 | F5: =MIN(F4,'Sources & Uses'!$D$4*'Transaction Assumptions'!$B$9) -> 77.4675
A6: Optional prepayment (cash sweep) | B6: =MIN(B4-B5,'Cash Flow & Returns'!B10) -> 0 | C6: =MIN(C4-C5,'Cash Flow & Returns'!C10) -> 0 | D6: =MIN(D4-D5,'Cash Flow & Returns'!D10) -> 0 | E6: =MIN(E4-E5,'Cash Flow & Returns'!E10) -> 0 | F6: =MIN(F4-F5,'Cash Flow & Returns'!F10) -> 0
A7: Total debt paydown | B7: =B5+B6 -> 77.4675 | C7: =C5+C6 -> 77.4675 | D7: =D5+D6 -> 77.4675 | E7: =E5+E6 -> 77.4675 | F7: =F5+F6 -> 77.4675
A8: Closing Term Loan balance | B8: =B4-B7 -> 1471.8825 | C8: =C4-C7 -> 1394.415 | D8: =D4-D7 -> 1316.9475 | E8: =E4-E7 -> 1239.48 | F8: =F4-F7 -> 1162.0125
A9: Average balance (for interest calc) | B9: =B4 -> 1549.35 | C9: =C4 -> 1471.8825 | D9: =D4 -> 1394.415 | E9: =E4 -> 1316.9475 | F9: =F4 -> 1239.48
A10: Interest expense | B10: =B9*'Transaction Assumptions'!$B$8 -> 138.9767 | C10: =C9*'Transaction Assumptions'!$B$8 -> 132.02786 | D10: =D9*'Transaction Assumptions'!$B$8 -> 125.07903 | E10: =E9*'Transaction Assumptions'!$B$8 -> 118.13019 | F10: =F9*'Transaction Assumptions'!$B$8 -> 111.18136
A12: Interest is calculated on the OPENING Term Loan balance each year, not the average of opening/closing. A true average-balance calc creates a circular
A13: reference (interest -> net income -> cash swept -> closing balance -> average balance -> interest) that most spreadsheet engines only resolve with iterative
A14: calculation switched on. Opening-balance interest is a standard, transparent simplification and slightly OVERSTATES interest
A15: (and so is conservative for IRR) since it ignores the benefit of in-year paydown.

Sheet Income Statement
A1: Post-LBO Forecast Income Statement (£m)
A3: £m | B3: Year 1 | C3: Year 2 | D3: Year 3 | E3: Year 4 | F3: Year 5
A4: Revenue | B4: ='Transaction Assumptions'!F4*(1+'Transaction Assumptions'!B19) -> 2313.2656 | C4: =B4*(1+'Transaction Assumptions'!C19) -> 2475.1942 | D4: =C4*(1+'Transaction Assumptions'!D19) -> 2636.0818 | E4: =D4*(1+'Transaction Assumptions'!E19) -> 2794.2468 | F4: =E4*(1+'Transaction Assumptions'!F19) -> 2947.9303
A5: growth % | B5: ='Transaction Assumptions'!B19 -> 0.075 | C5: ='Transaction Assumptions'!C19 -> 0.07 | D5: ='Transaction Assumptions'!D19 -> 0.065 | E5: ='Transaction Assumptions'!E19 -> 0.06 | F5: ='Transaction Assumptions'!F19 -> 0.055
A6: EBITDA | B6: =B4*'Transaction Assumptions'!B20 -> 377.0623 | C6: =C4*'Transaction Assumptions'!C20 -> 410.88224 | D6: =D4*'Transaction Assumptions'!D20 -> 445.49783 | E6: =E4*'Transaction Assumptions'!E20 -> 480.61044 | F6: =F4*'Transaction Assumptions'!F20 -> 515.88781
A7: margin % | B7: ='Transaction Assumptions'!B20 -> 0.163 | C7: ='Transaction Assumptions'!C20 -> 0.166 | D7: ='Transaction Assumptions'!D20 -> 0.169 | E7: ='Transaction Assumptions'!E20 -> 0.172 | F7: ='Transaction Assumptions'!F20 -> 0.175
A8: D&A | B8: =B4*$B$14 -> 97.157156 | C8: =C4*$B$14 -> 103.95816 | D8: =D4*$B$14 -> 110.71544 | E8: =E4*$B$14 -> 117.35836 | F8: =F4*$B$14 -> 123.81307
A9: EBIT | B9: =B6-B8 -> 279.90514 | C9: =C6-C8 -> 306.92408 | D9: =D6-D8 -> 334.78239 | E9: =E6-E8 -> 363.25208 | F9: =F6-F8 -> 392.07473
A10: Interest expense (Term Loan) | B10: ='Debt Schedule'!B10 -> 138.9767 | C10: ='Debt Schedule'!C10 -> 132.02786 | D10: ='Debt Schedule'!D10 -> 125.07903 | E10: ='Debt Schedule'!E10 -> 118.13019 | F10: ='Debt Schedule'!F10 -> 111.18136
A11: Pre-tax income | B11: =B9-B10 -> 140.92845 | C11: =C9-C10 -> 174.89622 | D11: =D9-D10 -> 209.70337 | E11: =E9-E10 -> 245.12189 | F11: =F9-F10 -> 280.89338
A12: Tax | B12: =MAX(B11,0)*'Transaction Assumptions'!$B$13 -> 35.232111 | C12: =MAX(C11,0)*'Transaction Assumptions'!$B$13 -> 43.724056 | D12: =MAX(D11,0)*'Transaction Assumptions'!$B$13 -> 52.425842 | E12: =MAX(E11,0)*'Transaction Assumptions'!$B$13 -> 61.280472 | F12: =MAX(F11,0)*'Transaction Assumptions'!$B$13 -> 70.223344
A13: Net Income | B13: =B11-B12 -> 105.69633 | C13: =C11-C12 -> 131.17217 | D13: =D11-D12 -> 157.27753 | E13: =E11-E12 -> 183.84142 | F13: =F11-F12 -> 210.67003
A14: D&A (% of revenue, held at FY2025 actual 4.2%) | B14: 0.042
A16: Note: base-year (T=0) Revenue in the Transaction Assumptions tab uses the FY2025 EBITDA-implied revenue base (EBITDA/margin) for consistency.

Sheet Cash Flow & Returns
A1: Cash Flow Available for Debt Paydown & Sponsor Returns
A3: £m | B3: Year 1 | C3: Year 2 | D3: Year 3 | E3: Year 4 | F3: Year 5
A4: Net Income | B4: ='Income Statement'!B13 -> 105.69633 | C4: ='Income Statement'!C13 -> 131.17217 | D4: ='Income Statement'!D13 -> 157.27753 | E4: ='Income Statement'!E13 -> 183.84142 | F4: ='Income Statement'!F13 -> 210.67003
A5: Add back: D&A | B5: ='Income Statement'!B8 -> 97.157156 | C5: ='Income Statement'!C8 -> 103.95816 | D5: ='Income Statement'!D8 -> 110.71544 | E5: ='Income Statement'!E8 -> 117.35836 | F5: ='Income Statement'!F8 -> 123.81307
A6: Less: CapEx | B6: =-'Income Statement'!B4*$B$12 -> -282.21841 | C6: =-'Income Statement'!C4*$B$12 -> -301.97369 | D6: =-'Income Statement'!D4*$B$12 -> -321.60198 | E6: =-'Income Statement'!E4*$B$12 -> -340.8981 | F6: =-'Income Statement'!F4*$B$12 -> -359.6475
A7: Less: Increase in NWC | B7: =-'Income Statement'!B4*'Transaction Assumptions'!B19*0.03 -> -5.2048477 | C7: =-'Income Statement'!C4*'Transaction Assumptions'!C19*0.03 -> -5.1979079 | D7: =-'Income Statement'!D4*'Transaction Assumptions'!D19*0.03 -> -5.1403596 | E7: =-'Income Statement'!E4*'Transaction Assumptions'!E19*0.03 -> -5.0296442 | F7: =-'Income Statement'!F4*'Transaction Assumptions'!F19*0.03 -> -4.864085
A8: Less: Mandatory amortisation | B8: =-'Debt Schedule'!B5 -> -77.4675 | C8: =-'Debt Schedule'!C5 -> -77.4675 | D8: =-'Debt Schedule'!D5 -> -77.4675 | E8: =-'Debt Schedule'!E5 -> -77.4675 | F8: =-'Debt Schedule'!F5 -> -77.4675
A9: Cash available before sweep | B9: =SUM(B4:B8) -> -162.03726 | C9: =SUM(C4:C8) -> -149.50878 | D9: =SUM(D4:D8) -> -136.21688 | E9: =SUM(E4:E8) -> -122.19547 | F9: =SUM(F4:F8) -> -107.49598
A10: Cash swept (80%) -> Optional prepayment | B10: =MAX(B9,0)*'Transaction Assumptions'!$B$10 -> 0 | C10: =MAX(C9,0)*'Transaction Assumptions'!$B$10 -> 0 | D10: =MAX(D9,0)*'Transaction Assumptions'!$B$10 -> 0 | E10: =MAX(E9,0)*'Transaction Assumptions'!$B$10 -> 0 | F10: =MAX(F9,0)*'Transaction Assumptions'!$B$10 -> 0
A12: CapEx (% of revenue, FY2025 actual) | B12: 0.122
A13: NWC change assumed proportional to revenue growth at 3% of revenue (FY2025 Working Capital was negative/-7.1% of revenue — modest cash-generative NWC dynamic for a cash retail business).
A15: EXIT & RETURNS
A16: Year 5 EBITDA | B16: ='Income Statement'!F6 -> 515.88781
A17: Exit EV/EBITDA multiple | B17: ='Transaction Assumptions'!B15 -> 6.2
A18: Exit Enterprise Value | B18: =B16*B17 -> 3198.5044
A19: Less: remaining Term Loan balance (Year 5 close) | B19: =-'Debt Schedule'!F8 -> -1162.0125
A20: Exit Equity Value | B20: =B18+B19 -> 2036.4919
A22: Initial Sponsor Equity | B22: ='Sources & Uses'!D6 -> 628.0032
A23: MOIC = Exit Equity / Initial Equity | B23: =B20/B22 -> 3.242805
A25: IRR cash flow (Year 0-5) | B25: =-B22 -> -628.0032 | C25: =0 -> 0 | D25: =0 -> 0 | E25: =0 -> 0 | F25: =0 -> 0 | G25: =B20 -> 2036.4919
A26: IRR (Excel IRR function) | B26: =IRR(B25:G25) -> 0.26527278
A28: MOIC and IRR assume no interim dividends to the sponsor (all cash flow used for debt paydown) — standard base-case LBO convention.
A29: 'Cash available before sweep' is negative in every year, so the cash sweep never triggers (Optional prepayment = £0 each year) —
A30: the Term Loan only pays down via the 5%/yr mandatory schedule. This is because Greggs' capex (~12% of revenue, reflecting an aggressive UK store rollout — FY2025
A31: actual) structurally exceeds D&A (~4-5% of revenue), a real feature of this business, not a modelling artefact. The 26.5% IRR / 3.2x MOIC is therefore driven almost
A32: entirely by EBITDA growth and margin expansion, NOT by deleveraging — an important caveat for any real credit or investment committee memo on this target.

Sheet Sensitivity
A1: Sensitivity — MOIC vs Entry Multiple and Exit Multiple
A2: This grid re-derives Sponsor Equity and Exit Equity algebraically for each Entry x Exit multiple pair, holding leverage, the debt paydown path, and
A3: operating assumptions fixed at the base case (a transparent simplification — a full rebuild of the debt schedule per cell is beyond a CV-level model).
A4: MOIC is shown (not IRR) because MOIC is a simple ratio with no convergence risk; IRR moves in the same direction as MOIC for a fixed 5-year hold.
A6: Entry \ Exit multiple | B6: 5.2 | C6: 5.7 | D6: 6.2 | E6: 6.7 | F6: 7.2
A7: 5.2 | B7: =(('Cash Flow & Returns'!$B$16*B$6-'Debt Schedule'!$F$8)/((('Transaction Assumptions'!$B$4*$A7)*(1+'Transaction Assumptions'!$B$6))-'Sources & Uses'!$D$4)) -> 5.4931706 | C7: =(('Cash Flow & Returns'!$B$16*C$6-'Debt Schedule'!$F$8)/((('Transaction Assumptions'!$B$4*$A7)*(1+'Transaction Assumptions'!$B$6))-'Sources & Uses'!$D$4)) -> 6.4249909 | D7: =(('Cash Flow & Returns'!$B$16*D$6-'Debt Schedule'!$F$8)/((('Transaction Assumptions'!$B$4*$A7)*(1+'Transaction Assumptions'!$B$6))-'Sources & Uses'!$D$4)) -> 7.3568113 | E7: =(('Cash Flow & Returns'!$B$16*E$6-'Debt Schedule'!$F$8)/((('Transaction Assumptions'!$B$4*$A7)*(1+'Transaction Assumptions'!$B$6))-'Sources & Uses'!$D$4)) -> 8.2886317 | F7: =(('Cash Flow & Returns'!$B$16*F$6-'Debt Schedule'!$F$8)/((('Transaction Assumptions'!$B$4*$A7)*(1+'Transaction Assumptions'!$B$6))-'Sources & Uses'!$D$4)) -> 9.220452
A8: 5.7 | B8: =(('Cash Flow & Returns'!$B$16*B$6-'Debt Schedule'!$F$8)/((('Transaction Assumptions'!$B$4*$A8)*(1+'Transaction Assumptions'!$B$6))-'Sources & Uses'!$D$4)) -> 3.3611181 | C8: =(('Cash Flow & Returns'!$B$16*C$6-'Debt Schedule'!$F$8)/((('Transaction Assumptions'!$B$4*$A8)*(1+'Transaction Assumptions'!$B$6))-'Sources & Uses'!$D$4)) -> 3.931273 | D8: =(('Cash Flow & Returns'!$B$16*D$6-'Debt Schedule'!$F$8)/((('Transaction Assumptions'!$B$4*$A8)*(1+'Transaction Assumptions'!$B$6))-'Sources & Uses'!$D$4)) -> 4.5014279 | E8: =(('Cash Flow & Returns'!$B$16*E$6-'Debt Schedule'!$F$8)/((('Transaction Assumptions'!$B$4*$A8)*(1+'Transaction Assumptions'!$B$6))-'Sources & Uses'!$D$4)) -> 5.0715828 | F8: =(('Cash Flow & Returns'!$B$16*F$6-'Debt Schedule'!$F$8)/((('Transaction Assumptions'!$B$4*$A8)*(1+'Transaction Assumptions'!$B$6))-'Sources & Uses'!$D$4)) -> 5.6417378
A9: 6.2 | B9: =(('Cash Flow & Returns'!$B$16*B$6-'Debt Schedule'!$F$8)/((('Transaction Assumptions'!$B$4*$A9)*(1+'Transaction Assumptions'!$B$6))-'Sources & Uses'!$D$4)) -> 2.4213318 | C9: =(('Cash Flow & Returns'!$B$16*C$6-'Debt Schedule'!$F$8)/((('Transaction Assumptions'!$B$4*$A9)*(1+'Transaction Assumptions'!$B$6))-'Sources & Uses'!$D$4)) -> 2.8320684 | D9: =(('Cash Flow & Returns'!$B$16*D$6-'Debt Schedule'!$F$8)/((('Transaction Assumptions'!$B$4*$A9)*(1+'Transaction Assumptions'!$B$6))-'Sources & Uses'!$D$4)) -> 3.242805 | E9: =(('Cash Flow & Returns'!$B$16*E$6-'Debt Schedule'!$F$8)/((('Transaction Assumptions'!$B$4*$A9)*(1+'Transaction Assumptions'!$B$6))-'Sources & Uses'!$D$4)) -> 3.6535416 | F9: =(('Cash Flow & Returns'!$B$16*F$6-'Debt Schedule'!$F$8)/((('Transaction Assumptions'!$B$4*$A9)*(1+'Transaction Assumptions'!$B$6))-'Sources & Uses'!$D$4)) -> 4.0642782
A10: 6.7 | B10: =(('Cash Flow & Returns'!$B$16*B$6-'Debt Schedule'!$F$8)/((('Transaction Assumptions'!$B$4*$A10)*(1+'Transaction Assumptions'!$B$6))-'Sources & Uses'!$D$4)) -> 1.892249 | C10: =(('Cash Flow & Returns'!$B$16*C$6-'Debt Schedule'!$F$8)/((('Transaction Assumptions'!$B$4*$A10)*(1+'Transaction Assumptions'!$B$6))-'Sources & Uses'!$D$4)) -> 2.213236 | D10: =(('Cash Flow & Returns'!$B$16*D$6-'Debt Schedule'!$F$8)/((('Transaction Assumptions'!$B$4*$A10)*(1+'Transaction Assumptions'!$B$6))-'Sources & Uses'!$D$4)) -> 2.5342229 | E10: =(('Cash Flow & Returns'!$B$16*E$6-'Debt Schedule'!$F$8)/((('Transaction Assumptions'!$B$4*$A10)*(1+'Transaction Assumptions'!$B$6))-'Sources & Uses'!$D$4)) -> 2.8552099 | F10: =(('Cash Flow & Returns'!$B$16*F$6-'Debt Schedule'!$F$8)/((('Transaction Assumptions'!$B$4*$A10)*(1+'Transaction Assumptions'!$B$6))-'Sources & Uses'!$D$4)) -> 3.1761968
A11: 7.2 | B11: =(('Cash Flow & Returns'!$B$16*B$6-'Debt Schedule'!$F$8)/((('Transaction Assumptions'!$B$4*$A11)*(1+'Transaction Assumptions'!$B$6))-'Sources & Uses'!$D$4)) -> 1.5529216 | C11: =(('Cash Flow & Returns'!$B$16*C$6-'Debt Schedule'!$F$8)/((('Transaction Assumptions'!$B$4*$A11)*(1+'Transaction Assumptions'!$B$6))-'Sources & Uses'!$D$4)) -> 1.8163476 | D11: =(('Cash Flow & Returns'!$B$16*D$6-'Debt Schedule'!$F$8)/((('Transaction Assumptions'!$B$4*$A11)*(1+'Transaction Assumptions'!$B$6))-'Sources & Uses'!$D$4)) -> 2.0797737 | E11: =(('Cash Flow & Returns'!$B$16*E$6-'Debt Schedule'!$F$8)/((('Transaction Assumptions'!$B$4*$A11)*(1+'Transaction Assumptions'!$B$6))-'Sources & Uses'!$D$4)) -> 2.3431997 | F11: =(('Cash Flow & Returns'!$B$16*F$6-'Debt Schedule'!$F$8)/((('Transaction Assumptions'!$B$4*$A11)*(1+'Transaction Assumptions'!$B$6))-'Sources & Uses'!$D$4)) -> 2.6066257
A13: Sponsor equity at each entry multiple = (Entry EV x (1+fee%)) - Term Loan (Term Loan held fixed at 4.5x EBITDA, base case). Exit equity = Year-5 EBITDA x exit
A14: multiple - Year-5 remaining Term Loan (base-case debt paydown path, unaffected by entry price since the loan is sized off EBITDA, not purchase price).

Sheet Sources
A1: Data Sources
A3: Item | B3: Source / URL
A4: Income Statement (FY2021-25) | B4: https://stockanalysis.com/quote/lon/GRG/financials/ — pulled 15 Aug 2026
A5: Statistics (EV, EV/EBITDA, net debt, beta) | B5: https://stockanalysis.com/quote/lon/GRG/statistics/ — pulled 15 Aug 2026
A6: BoE Bank Rate (for illustrative loan pricing) | B6: Bank of England, ~4.0% as at Aug 2026 (Bank Rate held per MPC July 2026 decision)
