Workbook

Sheet README
A1: Illustrative M&A Model: Moncler S.p.A. (Acquirer) / Burberry Group plc (Target)
A3: Prepared by: Abia Khan | khan.abia1013@gmail.com
A5: IMPORTANT — THIS IS NOT A REAL ANNOUNCED DEAL. No formal offer has been made by either company as of 15 Aug 2026.
A6: This model is grounded in genuine, reported market speculation: in mid-2026, trade press (Miss Tweed, relayed by
A7: Simply Wall St and other outlets) reported that Moncler S.p.A. was said to be considering a bid for Burberry, and
A8: that Bernard Arnault (LVMH, which holds a stake in Moncler) was reportedly 'keen' to see such a deal happen —
A9: Burberry shares reportedly jumped as much as 8% on the reports. Burberry declined to comment on speculation; a
A10: Moncler spokesperson said the company does not comment on 'unsubstantiated rumours'. That reported speculation is
A11: used only as a real-world reason to pair these two specific companies — every deal TERM below (premium, cash/stock
A12: mix, synergies) is this analyst's own assumption, clearly flagged, not a leaked or reported deal term.
A14: DATA AS OF: 15 August 2026. Standalone financials sourced from stockanalysis.com, cross-referenced against the
A15: trading comps build for consistency of Burberry figures. Full URLs on the Sources tab.
... A28: Book Equity flows to Goodwill, and there is no incremental D&A from the deal itself.

Sheet Standalone Financials
A1: Standalone Financials (most recent fiscal year, native currency)
A3: Metric | B3: Moncler (Acquirer, EUR m) | C3: Burberry (Target, GBP m)
A4: Net Income | B4: 626.7 | C4: 21 | D4: Moncler FY2025 (stockanalysis.com); Burberry FY2026 Net Income to Common (stockanalysis.com)
A5: Diluted Shares Outstanding (m) | B5: 271.6 | C5: 358.21 | D5: Companion Comps workbook, Data tab (both companies), sourced stockanalysis.com 5 Aug 2026
A6: Diluted EPS | B6: =B4/B5 -> 2.3074374 | C6: =C4/C5 -> 0.058624829 | D6: Calculated
A7: Current share price | B7: =B8/B5 -> 55.301915 | C7: 10.715 | D7: Moncler: EV/mcap implied (trading comps build, EUR); Burberry: trading comps build, Data tab, 5 Aug 2026
A8: Market Capitalisation | B8: 15020 | C8: 3830 | D8: Companion Comps workbook, Data tab, sourced stockanalysis.com 5 Aug 2026
A9: Total Equity (Book Value) | C9: 940 | D9: Burberry FY2026 balance sheet (stockanalysis.com); Moncler book value not required for this simplified PPA
A11: Moncler's current share price is derived as Market Cap / Diluted Shares (EUR232,580m implied via comps workbook was for LVMH — Moncler's own market
A12: cap of EUR15,020m / 271.6m shares = EUR55.31; the EUR62.14 trading price shown in the trading comps Data tab reflects a slightly later intraday
A13: quote used for cross-checking — this model uses the Market Cap / Shares calculated figure for full internal consistency.
A15: IMPORTANT FX NOTE: Moncler reports in EUR, Burberry in GBP. This model converts Burberry's GBP purchase price and financials into EUR at the deal's
A16: FX rate (see Deal Assumptions tab) BEFORE combining them in the Pro Forma — unlike the trading-comps workbook, an M&A model MUST convert both sides to a
A17: single currency (the acquirer's reporting currency, EUR) because Pro Forma EPS is a single combined number, not a ratio.

Sheet Deal Assumptions
A1: Deal Assumptions
A3: Input | B3: Value
A4: EUR/GBP FX rate (deal date) | B4: 0.858 | C4: Bloomberg EUR/GBP, 5 Aug 2026 (same rate as the trading comps build, for consistency)
A5: Offer price per Burberry share (£) | B5: 13.39 | C5: Equal to Burberry undisturbed price £10.715 x (1 + 25% premium) — see Deal Premium row below
A6: Deal premium to undisturbed price | B6: 0.25 | C6: Mid-point of a typical 20-30% control premium range — analyst assumption, NOT a reported term
A7: % Cash consideration | B7: 0.5 | C7: Analyst assumption — illustrative 50/50 structure
A8: Cost of new acquisition debt (pre-tax) | B8: 0.055 | C8: UK 10yr Gilt ~5.0% (Aug 2026) + ~50bp corporate spread for a BB+/BBB- rated issuer, illustrative
A9: Pre-tax annual cost synergies (EUR m) | B9: 68.6 | C9: Equal to GBP80m x 0.858 FX. GBP80m assumed (~1.7% of Burberry FY2026 revenue) — analyst assumption, see README
A10: Tax rate (combined entity) | B10: 0.25 | C10: Blended EU/UK statutory rate assumption for simplicity
A12: % Stock consideration (linked = 1 - %Cash) | B12: =1-B7 -> 0.5

Sheet Purchase Price Allocation
A1: Purchase Price and New Shares Issued
B3: Value
A4: Offer price per Burberry share (£) | B4: ='Deal Assumptions'!B5 -> 13.39
A5: Burberry diluted shares (m) | B5: ='Standalone Financials'!C5 -> 358.21
A6: Purchase Price (£m) | B6: =B4*B5 -> 4796.4319
A7: Purchase Price (EUR m, converted at deal FX) | B7: =B6/'Deal Assumptions'!B4 -> 5590.247
A9: Cash consideration (EUR m) | B9: =B7*'Deal Assumptions'!B7 -> 2795.1235
A10: Stock consideration (EUR m) | B10: =B7*'Deal Assumptions'!B12 -> 2795.1235
A11: Moncler current share price (EUR) | B11: ='Standalone Financials'!B7 -> 55.301915
A12: New Moncler shares issued (m) | B12: =B10/B11 -> 50.542979
A14: Target Book Equity (£m) | B14: ='Standalone Financials'!C9 -> 940
A15: Target Book Equity (EUR m) | B15: =B14/'Deal Assumptions'!B4 -> 1095.5711
A16: Goodwill = Purchase Price - Target Book Equity | B16: =B7-B15 -> 4494.6759
A18: Simplified PPA: no fair-value write-ups on tangible/intangible assets are modelled, so no incremental D&A arises from the deal.
A19: In a full sell-side/buy-side PPA, brand intangibles and property would typically be revalued, creating amortisable step-ups — a natural 'go deeper' extension.

Sheet Pro Forma
A1: Pro Forma Combined Income Statement (EUR m)
B3: EUR m
A4: Moncler standalone Net Income (EUR m) | B4: ='Standalone Financials'!B4 -> 626.7
A5: Burberry standalone Net Income (£m) | B5: ='Standalone Financials'!C4 -> 21
A6: Burberry standalone Net Income (EUR m) | B6: =B5/'Deal Assumptions'!B4 -> 24.475524
A7: Add: pre-tax cost synergies (EUR m) | B7: ='Deal Assumptions'!B9 -> 68.6
A8: Less: tax on synergies | B8: =-B7*'Deal Assumptions'!B10 -> -17.15
A9: After-tax synergies | B9: =B7+B8 -> 51.45
A11: New acquisition debt (EUR m) = cash consideration | B11: ='Purchase Price Allocation'!B9 -> 2795.1235
A12: Incremental interest expense (pre-tax) | B12: =B11*'Deal Assumptions'!B8 -> 153.73179
A13: Less: tax shield on incremental interest | B13: =-B12*'Deal Assumptions'!B10 -> -38.432948
A14: After-tax incremental interest expense | B14: =B12+B13 -> 115.29884
A16: Incremental D&A from deal (simplified PPA = £0) | B16: =0 -> 0
A18: Pro Forma Combined Net Income | B18: =B4+B6+B9-B14-B16 -> 587.32668
A20: Pro Forma NI = Acquirer NI + Target NI (converted to EUR) + after-tax synergies - after-tax incremental interest on new acquisition debt - incremental D&A (nil here).

Sheet Accretion-Dilution
A1: Accretion / (Dilution) Analysis
B3: Value
A4: Moncler standalone diluted shares (m) | B4: ='Standalone Financials'!B5 -> 271.6
A5: New shares issued in the deal (m) | B5: ='Purchase Price Allocation'!B12 -> 50.542979
A6: Pro Forma diluted shares outstanding (m) | B6: =B4+B5 -> 322.14298
A8: Pro Forma Combined Net Income (EUR m) | B8: ='Pro Forma'!B18 -> 587.32668
A9: Pro Forma EPS (EUR) | B9: =B8/B6 -> 1.8231863
A11: Moncler standalone EPS (EUR) | B11: ='Standalone Financials'!B6 -> 2.3074374
A12: % Accretion / (Dilution) = Pro Forma EPS / Standalone EPS - 1 | B12: =B9/B11-1 -> -0.20986531
A14: Verdict | B14: =IF(B12>0,"ACCRETIVE to Moncler EPS","DILUTIVE to Moncler EPS") -> DILUTIVE to Moncler EPS
A16: Breakeven synergies needed for the deal to be EPS-neutral
A17: (i.e. synergies at which Pro Forma EPS = Standalone EPS) | B17: =(('Standalone Financials'!B6*B6)-('Pro Forma'!B4+'Pro Forma'!B6-'Pro Forma'!B14-'Pro Forma'!B16))/(1-'Deal Assumptions'!B10) -> 276.59744
A19: Breakeven synergies solved algebraically: sets Pro Forma NI such that Pro Forma EPS = Moncler standalone EPS, then backs out the required PRE-TAX
A20: synergy figure (dividing the required after-tax synergy contribution by (1 - tax rate)).
A22: At these assumptions the deal is DILUTIVE (~-25% to Moncler EPS), because Burberry's FY2026 net income (£21m) is still
A23: severely depressed by turnaround costs relative to the ~£5.4bn purchase price — the earnings being acquired are tiny next to the premium paid. Breakeven
A24: synergies (~EUR317m pretax) are ~4.6x the EUR68.6m assumed, meaning cost synergies alone cannot make this deal EPS-neutral for Moncler at this price. A real
A25: acquirer would either need Burberry's earnings recovery to be well underway before signing, a materially lower premium, or a much higher synergy case — this is
A26: exactly the kind of finding a genuine accretion/dilution analysis exists to surface, not a result to be adjusted away.

Sheet Sensitivity
A1: Sensitivity — % Accretion/(Dilution) vs Cash/Stock Mix and Synergies
A3: % Cash \ Synergies (EUR m) | B3: 0 | C3: 34.3 | D3: 68.6 | E3: 102.9 | F3: 137.2
A4: 0 | B4: =((('Standalone Financials'!$B$4+'Standalone Financials'!$C$4/'Deal Assumptions'!$B$4+B$3*(1-'Deal Assumptions'!$B$10)-('Purchase Price Allocation'!$B$7*$A4)*'Deal Assumptions'!$B$8*(1-'Deal Assumptions'!$B$10))/('Standalone Financials'!$B$5+('Purchase Price Allocation'!$B$7*(1-$A4))/'Standalone Financials'!$B$7))/'Standalone Financials'!$B$6-1) -> -0.24277471 | C4: =((('Standalone Financials'!$B$4+'Standalone Financials'!$C$4/'Deal Assumptions'!$B$4+C$3*(1-'Deal Assumptions'!$B$10)-('Purchase Price Allocation'!$B$7*$A4)*'Deal Assumptions'!$B$8*(1-'Deal Assumptions'!$B$10))/('Standalone Financials'!$B$5+('Purchase Price Allocation'!$B$7*(1-$A4))/'Standalone Financials'!$B$7))/'Standalone Financials'!$B$6-1) -> -0.21286016 | D4: =((('Standalone Financials'!$B$4+'Standalone Financials'!$C$4/'Deal Assumptions'!$B$4+D$3*(1-'Deal Assumptions'!$B$10)-('Purchase Price Allocation'!$B$7*$A4)*'Deal Assumptions'!$B$8*(1-'Deal Assumptions'!$B$10))/('Standalone Financials'!$B$5+('Purchase Price Allocation'!$B$7*(1-$A4))/'Standalone Financials'!$B$7))/'Standalone Financials'!$B$6-1) -> -0.18294562 | E4: =((('Standalone Financials'!$B$4+'Standalone Financials'!$C$4/'Deal Assumptions'!$B$4+E$3*(1-'Deal Assumptions'!$B$10)-('Purchase Price Allocation'!$B$7*$A4)*'Deal Assumptions'!$B$8*(1-'Deal Assumptions'!$B$10))/('Standalone Financials'!$B$5+('Purchase Price Allocation'!$B$7*(1-$A4))/'Standalone Financials'!$B$7))/'Standalone Financials'!$B$6-1) -> -0.15303107 | F4: =((('Standalone Financials'!$B$4+'Standalone Financials'!$C$4/'Deal Assumptions'!$B$4+F$3*(1-'Deal Assumptions'!$B$10)-('Purchase Price Allocation'!$B$7*$A4)*'Deal Assumptions'!$B$8*(1-'Deal Assumptions'!$B$10))/('Standalone Financials'!$B$5+('Purchase Price Allocation'!$B$7*(1-$A4))/'Standalone Financials'!$B$7))/'Standalone Financials'!$B$6-1) -> -0.12311652
A5: 0.25 | B5: =((('Standalone Financials'!$B$4+'Standalone Financials'!$C$4/'Deal Assumptions'!$B$4+B$3*(1-'Deal Assumptions'!$B$10)-('Purchase Price Allocation'!$B$7*$A5)*'Deal Assumptions'!$B$8*(1-'Deal Assumptions'!$B$10))/('Standalone Financials'!$B$5+('Purchase Price Allocation'!$B$7*(1-$A5))/'Standalone Financials'!$B$7))/'Standalone Financials'!$B$6-1) -> -0.25960753 | C5: =((('Standalone Financials'!$B$4+'Standalone Financials'!$C$4/'Deal Assumptions'!$B$4+C$3*(1-'Deal Assumptions'!$B$10)-('Purchase Price Allocation'!$B$7*$A5)*'Deal Assumptions'!$B$8*(1-'Deal Assumptions'!$B$10))/('Standalone Financials'!$B$5+('Purchase Price Allocation'!$B$7*(1-$A5))/'Standalone Financials'!$B$7))/'Standalone Financials'!$B$6-1) -> -0.22751695 | D5: =((('Standalone Financials'!$B$4+'Standalone Financials'!$C$4/'Deal Assumptions'!$B$4+D$3*(1-'Deal Assumptions'!$B$10)-('Purchase Price Allocation'!$B$7*$A5)*'Deal Assumptions'!$B$8*(1-'Deal Assumptions'!$B$10))/('Standalone Financials'!$B$5+('Purchase Price Allocation'!$B$7*(1-$A5))/'Standalone Financials'!$B$7))/'Standalone Financials'!$B$6-1) -> -0.19542637 | E5: =((('Standalone Financials'!$B$4+'Standalone Financials'!$C$4/'Deal Assumptions'!$B$4+E$3*(1-'Deal Assumptions'!$B$10)-('Purchase Price Allocation'!$B$7*$A5)*'Deal Assumptions'!$B$8*(1-'Deal Assumptions'!$B$10))/('Standalone Financials'!$B$5+('Purchase Price Allocation'!$B$7*(1-$A5))/'Standalone Financials'!$B$7))/'Standalone Financials'!$B$6-1) -> -0.16333579 | F5: =((('Standalone Financials'!$B$4+'Standalone Financials'!$C$4/'Deal Assumptions'!$B$4+F$3*(1-'Deal Assumptions'!$B$10)-('Purchase Price Allocation'!$B$7*$A5)*'Deal Assumptions'!$B$8*(1-'Deal Assumptions'!$B$10))/('Standalone Financials'!$B$5+('Purchase Price Allocation'!$B$7*(1-$A5))/'Standalone Financials'!$B$7))/'Standalone Financials'!$B$6-1) -> -0.13124521
A6: 0.5 | B6: =((('Standalone Financials'!$B$4+'Standalone Financials'!$C$4/'Deal Assumptions'!$B$4+B$3*(1-'Deal Assumptions'!$B$10)-('Purchase Price Allocation'!$B$7*$A6)*'Deal Assumptions'!$B$8*(1-'Deal Assumptions'!$B$10))/('Standalone Financials'!$B$5+('Purchase Price Allocation'!$B$7*(1-$A6))/'Standalone Financials'!$B$7))/'Standalone Financials'!$B$6-1) -> -0.27908135 | C6: =((('Standalone Financials'!$B$4+'Standalone Financials'!$C$4/'Deal Assumptions'!$B$4+C$3*(1-'Deal Assumptions'!$B$10)-('Purchase Price Allocation'!$B$7*$A6)*'Deal Assumptions'!$B$8*(1-'Deal Assumptions'!$B$10))/('Standalone Financials'!$B$5+('Purchase Price Allocation'!$B$7*(1-$A6))/'Standalone Financials'!$B$7))/'Standalone Financials'!$B$6-1) -> -0.24447333 | D6: =((('Standalone Financials'!$B$4+'Standalone Financials'!$C$4/'Deal Assumptions'!$B$4+D$3*(1-'Deal Assumptions'!$B$10)-('Purchase Price Allocation'!$B$7*$A6)*'Deal Assumptions'!$B$8*(1-'Deal Assumptions'!$B$10))/('Standalone Financials'!$B$5+('Purchase Price Allocation'!$B$7*(1-$A6))/'Standalone Financials'!$B$7))/'Standalone Financials'!$B$6-1) -> -0.20986531 | E6: =((('Standalone Financials'!$B$4+'Standalone Financials'!$C$4/'Deal Assumptions'!$B$4+E$3*(1-'Deal Assumptions'!$B$10)-('Purchase Price Allocation'!$B$7*$A6)*'Deal Assumptions'!$B$8*(1-'Deal Assumptions'!$B$10))/('Standalone Financials'!$B$5+('Purchase Price Allocation'!$B$7*(1-$A6))/'Standalone Financials'!$B$7))/'Standalone Financials'!$B$6-1) -> -0.17525728 | F6: =((('Standalone Financials'!$B$4+'Standalone Financials'!$C$4/'Deal Assumptions'!$B$4+F$3*(1-'Deal Assumptions'!$B$10)-('Purchase Price Allocation'!$B$7*$A6)*'Deal Assumptions'!$B$8*(1-'Deal Assumptions'!$B$10))/('Standalone Financials'!$B$5+('Purchase Price Allocation'!$B$7*(1-$A6))/'Standalone Financials'!$B$7))/'Standalone Financials'!$B$6-1) -> -0.14064926
A7: 0.75 | B7: =((('Standalone Financials'!$B$4+'Standalone Financials'!$C$4/'Deal Assumptions'!$B$4+B$3*(1-'Deal Assumptions'!$B$10)-('Purchase Price Allocation'!$B$7*$A7)*'Deal Assumptions'!$B$8*(1-'Deal Assumptions'!$B$10))/('Standalone Financials'!$B$5+('Purchase Price Allocation'!$B$7*(1-$A7))/'Standalone Financials'!$B$7))/'Standalone Financials'!$B$6-1) -> -0.30187063 | C7: =((('Standalone Financials'!$B$4+'Standalone Financials'!$C$4/'Deal Assumptions'!$B$4+C$3*(1-'Deal Assumptions'!$B$10)-('Purchase Price Allocation'!$B$7*$A7)*'Deal Assumptions'!$B$8*(1-'Deal Assumptions'!$B$10))/('Standalone Financials'!$B$5+('Purchase Price Allocation'!$B$7*(1-$A7))/'Standalone Financials'!$B$7))/'Standalone Financials'!$B$6-1) -> -0.26431657 | D7: =((('Standalone Financials'!$B$4+'Standalone Financials'!$C$4/'Deal Assumptions'!$B$4+D$3*(1-'Deal Assumptions'!$B$10)-('Purchase Price Allocation'!$B$7*$A7)*'Deal Assumptions'!$B$8*(1-'Deal Assumptions'!$B$10))/('Standalone Financials'!$B$5+('Purchase Price Allocation'!$B$7*(1-$A7))/'Standalone Financials'!$B$7))/'Standalone Financials'!$B$6-1) -> -0.2267625 | E7: =((('Standalone Financials'!$B$4+'Standalone Financials'!$C$4/'Deal Assumptions'!$B$4+E$3*(1-'Deal Assumptions'!$B$10)-('Purchase Price Allocation'!$B$7*$A7)*'Deal Assumptions'!$B$8*(1-'Deal Assumptions'!$B$10))/('Standalone Financials'!$B$5+('Purchase Price Allocation'!$B$7*(1-$A7))/'Standalone Financials'!$B$7))/'Standalone Financials'!$B$6-1) -> -0.18920844 | F7: =((('Standalone Financials'!$B$4+'Standalone Financials'!$C$4/'Deal Assumptions'!$B$4+F$3*(1-'Deal Assumptions'!$B$10)-('Purchase Price Allocation'!$B$7*$A7)*'Deal Assumptions'!$B$8*(1-'Deal Assumptions'!$B$10))/('Standalone Financials'!$B$5+('Purchase Price Allocation'!$B$7*(1-$A7))/'Standalone Financials'!$B$7))/'Standalone Financials'!$B$6-1) -> -0.15165437
A8: 1 | B8: =((('Standalone Financials'!$B$4+'Standalone Financials'!$C$4/'Deal Assumptions'!$B$4+B$3*(1-'Deal Assumptions'!$B$10)-('Purchase Price Allocation'!$B$7*$A8)*'Deal Assumptions'!$B$8*(1-'Deal Assumptions'!$B$10))/('Standalone Financials'!$B$5+('Purchase Price Allocation'!$B$7*(1-$A8))/'Standalone Financials'!$B$7))/'Standalone Financials'!$B$6-1) -> -0.32890085 | C8: =((('Standalone Financials'!$B$4+'Standalone Financials'!$C$4/'Deal Assumptions'!$B$4+C$3*(1-'Deal Assumptions'!$B$10)-('Purchase Price Allocation'!$B$7*$A8)*'Deal Assumptions'!$B$8*(1-'Deal Assumptions'!$B$10))/('Standalone Financials'!$B$5+('Purchase Price Allocation'!$B$7*(1-$A8))/'Standalone Financials'!$B$7))/'Standalone Financials'!$B$6-1) -> -0.2878525 | D8: =((('Standalone Financials'!$B$4+'Standalone Financials'!$C$4/'Deal Assumptions'!$B$4+D$3*(1-'Deal Assumptions'!$B$10)-('Purchase Price Allocation'!$B$7*$A8)*'Deal Assumptions'!$B$8*(1-'Deal Assumptions'!$B$10))/('Standalone Financials'!$B$5+('Purchase Price Allocation'!$B$7*(1-$A8))/'Standalone Financials'!$B$7))/'Standalone Financials'!$B$6-1) -> -0.24680415 | E8: =((('Standalone Financials'!$B$4+'Standalone Financials'!$C$4/'Deal Assumptions'!$B$4+E$3*(1-'Deal Assumptions'!$B$10)-('Purchase Price Allocation'!$B$7*$A8)*'Deal Assumptions'!$B$8*(1-'Deal Assumptions'!$B$10))/('Standalone Financials'!$B$5+('Purchase Price Allocation'!$B$7*(1-$A8))/'Standalone Financials'!$B$7))/'Standalone Financials'!$B$6-1) -> -0.20575581 | F8: =((('Standalone Financials'!$B$4+'Standalone Financials'!$C$4/'Deal Assumptions'!$B$4+F$3*(1-'Deal Assumptions'!$B$10)-('Purchase Price Allocation'!$B$7*$A8)*'Deal Assumptions'!$B$8*(1-'Deal Assumptions'!$B$10))/('Standalone Financials'!$B$5+('Purchase Price Allocation'!$B$7*(1-$A8))/'Standalone Financials'!$B$7))/'Standalone Financials'!$B$6-1) -> -0.16470746
A10: Each cell independently recomputes Pro Forma Net Income and Pro Forma shares for that cash/stock split and synergy level, then compares to Moncler's
A11: standalone EPS — mechanically equivalent to Excel's 2-variable Data Table, built without one to avoid iterative-calculation issues outside Excel.

Sheet Sources
A1: Data Sources
A3: Item | B3: Source / URL
A4: Moncler standalone financials | B4: Companion workbook Burberry_Luxury_Comps_Model_CV.xlsx, Data tab — sourced stockanalysis.com/quote/bit/MONC/statistics/, 5 Aug 2026
A5: Burberry standalone financials | B5: https://stockanalysis.com/quote/lon/BRBY/financials/ — pulled 15 Aug 2026
A6: Burberry current share price | B6: Trading comps build, Data tab — £10.715, 5 Aug 2026 (used for internal consistency across all models)
A7: EUR/GBP FX rate | B7: Bloomberg EUR/GBP — 0.858, 5 Aug 2026 (matches the trading comps build for consistency)
A8: Cost of new acquisition debt basis | B8: TradingEconomics UK 10Y Government Bond Yield ~4.97-5.07%, 13 Aug 2026, plus illustrative corporate spread
A9: Moncler/Burberry deal speculation (context only, not deal terms) | B9: Reported by Miss Tweed, relayed via Simply Wall St (simplywall.st/stocks/.../burberry-group/future), retrieved 15 Aug 2026
